{
    "boxShadow": "none",
    "widgetName": "Hypto_upi_id_input",
    "topRow": 0,
    "bottomRow": 4,
    "parentRowSpace": 40,
    "type": "INPUT_WIDGET",
    "parentColumnSpace": 71.5,
    "resetOnSubmit": false,
    "leftColumn": 0,
    "dynamicBindingPathList": [{"key": "accentColor"}],
    "inputType": "TEXT",
    "placeholderText": "hypto.wazirx000000000@icici, hypto.wazirx1111111111@icici",
    "isDisabled": false,
    "validation": "true",
    "labelTextSize": "0.875rem",
    "isRequired": false,
    "rightColumn": 18,
    "widgetId": "4oi6242zkv",
    "accentColor": "{{appsmith.theme.colors.primaryColor}}",
    "isVisible": true,
    "label": "",
    "version": 1,
    "parentId": "v68ybk3o2d",
    "isLoading": false,
    "borderRadius": "0px"
}